[
	{"name": "XS",
	 "bust": 32,
	 "waist": 28,
	 "hips": 34,
	 "across_shouler": 13 },
	{"name": "S",
	 "bust": 34,
	 "waist": 30,
	 "hips": 36,
	 "across_shouler": 13.5 },
	 {"name": "M",
	 "bust": 36,
	 "waist": 32,
	 "hips": 38,
	 "across_shouler": 14 },
	 {"name": "L",
	 "bust": 38,
	 "waist": 34,
	 "hips": 40,
	 "across_shouler": 14.5 },
	 {"name": "XL",
	 "bust": 40,
	 "waist": 36,
	 "hips": 42,
	 "across_shouler": 15 },
	 {"name": "XXL",
	 "bust": 42,
	 "waist": 38,
	 "hips": 44,
	 "across_shouler": 15.5 }
]
